riverrem/REMMaker.py
riverrem/RasterViz.py
riverrem/__init__.py
RiverREM-0.0.1.dist-info/METADATA
RiverREM-0.0.1.dist-info/WHEEL
RiverREM-0.0.1.dist-info/top_level.txt
RiverREM-0.0.1.dist-info/RECORD
